rd2md/__init__.py
rd2md/__main__.py
rd2md/_version.py
rd2md/classes.py
rd2md/parser.py
rd2md-1.0.1.dist-info/LICENSE
rd2md-1.0.1.dist-info/METADATA
rd2md-1.0.1.dist-info/WHEEL
rd2md-1.0.1.dist-info/entry_points.txt
rd2md-1.0.1.dist-info/top_level.txt
rd2md-1.0.1.dist-info/RECORD
