Metadata-Version: 2.1
Name: rd2md
Version: 1.0.1
Summary: Converter from R docs to markdown
Home-page: https://github.com/comet-ml/rd2md
Author: rd2md development team
License: MIT License
Keywords: python,r
Platform: Linux
Platform: Mac OS X
Platform: Windows
Classifier: License :: OSI Approved :: MIT License
Classifier: Programming Language :: Python
Classifier: Programming Language :: Python :: 3
Classifier: Programming Language :: Python :: 3.6
Classifier: Programming Language :: Python :: 3.7
Classifier: Programming Language :: Python :: 3.8
Classifier: Programming Language :: Python :: 3.9
Classifier: Programming Language :: Python :: 3.10
Requires-Python: >=3.6
License-File: LICENSE
